README.txt
setup.py
FileServer.egg-info/PKG-INFO
FileServer.egg-info/SOURCES.txt
FileServer.egg-info/dependency_links.txt
FileServer.egg-info/entry_points.txt
FileServer.egg-info/not-zip-safe
FileServer.egg-info/requires.txt
FileServer.egg-info/top_level.txt
fileserver/__init__.py
fileserver/web.py