Metadata-Version: 1.0
Name: FileServer
Version: 0.2.1
Summary: a simple static fileserver and directory index server in python (WSGI app)
Home-page: http://k0s.org/hg/FileServer
Author: Jeff Hammel
Author-email: jhammel@mozilla.com
License: MPL
Platform: UNKNOWN
